{
  "name": "Axon Ivy Dev Container",
  "build": {
    "dockerfile": "Dockerfile",
    "args": {
      "IVY_ENGINE_DOWNLOAD_URL": "https://dev.axonivy.com/permalink/dev/axonivy-engine-slim.zip"
    }
  },
  "forwardPorts": [8080],
  "postCreateCommand": "mkdir -p logs && rm -f logs/maven-nohup.out && nohup bash -c 'mvn dependency:go-offline &'> logs/maven-nohup.out",
  "postStartCommand": "mkdir -p logs && rm -f logs/eninge-nohup.out && nohup bash -c '/usr/lib/axonivy-engine/bin/AxonIvyEngine &'> logs/engine-nohup.out",
  "features": {
    "ghcr.io/devcontainers/features/java:1": {
      "version": "17",
      "installMaven": "true",
      "jdkDistro": "tem"
    }
  },
  "customizations": {
    "vscode": {
      "extensions": ["axon-ivy.designer-11"],
      "settings": {
        "engine.runByExtension": false,
        "engine.url": "http://localhost:8080/",
        "engine.directory": "/usr/lib/axonivy-engine"
      }
    }
  }
}
