{
    "installers": [
        {
            "id": "maven-import",
            "data": {
                "projects": [
                    {
                        "groupId": "com.axonivy.demo",
                        "artifactId": "quick-start-tutorial",
                        "version": "${version}",
                        "type": "iar"
                    }
                ],
                "repositories": [
                    {
                        "id": "maven.axonivy.com",
                        "url": "https://maven.axonivy.com",
                        "snapshots": {
                            "enabled": "true"
                        }
                    }
                ]
            }
        }
    ]
}
